{
  "include": [
    "panel.responsive_shipping_options",
    "panel.responsive_payment_guest_section",
    "panel.checkout_loyallist_section"
  ],

  "url":                     "/chkout/rc",
  "verify_page":             "id, rc-delivery-note-info || id, rc-order-summary-list",

  "technical_error_overlay": "id, rc-errorOverlay-action",
  "edit_button":             "id, rc-payment-edit",
  "payment_edit_button":     "id, rc-payment-edit",
  "submit_button":             "cssSelector, [type='submit']",
  "place_order":                "id, rc-place-order",
  "error_ok":                "id, rc-overlay-action",

  "3d_secure_reviewIframe":  "id, reviewIframe",
  "3d_secure_authIframe":    "id, authWindow",
  "3d_secure_password":      "name, external.field.password",
  "3d_secure_submit":        "name, UsernamePasswordEntry",

  "bops_shipping":           "id, rc-orderSummary-pickupInStore",
  "normal_shipping":         "id, rc-orderSummary-shippingCost",
  "continue_shipping_checkout_button": "id, rc-shipping-continue",

  "shipping_loading":        "className, loader-container",
  "loyallist_section_header": "class, loyallistHeader||class, rc-loyallist-header",

  "create_profile_email_exist_error": "xpath,//input[@id='rc-payment-email']/following-sibling::small",
  "create_profile_pwd": "id, profile.password",
  "create_profile_date_list":   "xpath, //div[@class='custom dropdown rc-profile-field']",
  "create_profile_date_options":   "xpath, //div[@class='custom dropdown rc-profile-field open']//ul/li",
  "create_profile_email": "id, billingContact.email",
  "privacy_info": "class, rc-ca-privacy"
}